[{"id":981,"first_name":"Rhona","last_name":"Svanetti","email":"rsvanettir8@123-reg.co.uk","gender":"Female","phone":"739-814-1714"},{"id":982,"first_name":"Ryun","last_name":"Conws","email":"rconwsr9@soundcloud.com","gender":"Male","phone":"113-422-5078"},{"id":983,"first_name":"Shalom","last_name":"Tolomelli","email":"stolomellira@telegraph.co.uk","gender":"Male","phone":"759-349-6977"},{"id":984,"first_name":"Nigel","last_name":"Bamell","email":"nbamellrb@myspace.com","gender":"Male","phone":"115-588-4306"},{"id":985,"first_name":"Alain","last_name":"Sheere","email":"asheererc@elpais.com","gender":"Male","phone":"332-526-1854"},{"id":986,"first_name":"Giffard","last_name":"Gilhooley","email":"ggilhooleyrd@ebay.com","gender":"Male","phone":"642-954-9970"},{"id":987,"first_name":"Trixie","last_name":"Willimont","email":"twillimontre@163.com","gender":"Female","phone":"247-274-8617"},{"id":988,"first_name":"Wendall","last_name":"Cuvley","email":"wcuvleyrf@wikia.com","gender":"Male","phone":"454-783-7877"},{"id":989,"first_name":"Freemon","last_name":"Kenneway","email":"fkennewayrg@theguardian.com","gender":"Male","phone":"896-436-2146"},{"id":990,"first_name":"Hayden","last_name":"Crusham","email":"hcrushamrh@qq.com","gender":"Male","phone":"818-125-5239"}]